{
  "kind": "collectionType",
  "collectionName": "homes",
  "info": {
    "singularName": "home",
    "pluralName": "homes",
    "displayName": "home",
    "description": ""
  },
  "options": {
    "draftAndPublish": true
  },
  "pluginOptions": {},
  "attributes": {
    "name": {
      "type": "string"
    },
    "items": {
      "type": "dynamiczone",
      "components": [
        "home.items-confian",
        "home.items-carrusel",
        "home.items-servicios",
        "home.items-caso",
        "home.items-articulos",
        "home.items-contacto"
      ]
    }
  }
}
